{
  "date": "2026-06-15",
  "scan_version": "1.3",
  "market_regime": "NORMAL",
  "twii_vs_ma60": "N/A",
  "entry_threshold": "≥2/4條件",
  "uncertainty_threshold": 0.025806,
  "total_scanned": 50,
  "buy_signals": [
    {
      "ticker": "2832",
      "alpha_5d": 0.12,
      "alpha_20d": 0.2105,
      "alpha_60d": 0.1791,
      "sharpe": 8.602,
      "confidence": "高信心",
      "uncertainty": 0.024,
      "suggested_weight": 0.1076,
      "score": 115,
      "base_score": 75,
      "conditions_met": 3,
      "conditions_total": 4,
      "rank_stability": {
        "met": true,
        "detail": "Top 10 連續 3 天",
        "top10_streak": 3,
        "top50_streak": 5
      },
      "high_confidence": {
        "met": true,
        "detail": "Uncertainty=0.0240 ✓ (<0.0258)"
      },
      "relative_low": {
        "met": true,
        "detail": "RSI=47, 價格<MA20 (53.3<53.8)",
        "rsi": 47.4,
        "below_ma20": true
      },
      "institutional_buy": {
        "met": false,
        "detail": "無此股機構資料"
      },
      "pattern": {
        "pattern_score": 84,
        "pattern_id": "w_bottom",
        "pattern_name": "W底（雙底）",
        "failure_stop": 52.9,
        "target_price": 56.65,
        "dual_confirm": true,
        "pattern_bonus": 40
      }
    },
    {
      "ticker": "6023",
      "alpha_5d": 0.1032,
      "alpha_20d": 0.1705,
      "alpha_60d": 0.1304,
      "sharpe": 7.794,
      "confidence": "高信心",
      "uncertainty": 0.0214,
      "suggested_weight": 0.0974,
      "score": 105,
      "base_score": 55,
      "conditions_met": 2,
      "conditions_total": 4,
      "rank_stability": {
        "met": true,
        "detail": "Top 50 連續 5 天",
        "top10_streak": 0,
        "top50_streak": 5
      },
      "high_confidence": {
        "met": true,
        "detail": "Uncertainty=0.0214 ✓ (<0.0258)"
      },
      "relative_low": {
        "met": false,
        "detail": "RSI=52, 價格>MA20",
        "rsi": 52.3,
        "below_ma20": false
      },
      "institutional_buy": {
        "met": false,
        "detail": "無此股機構資料"
      },
      "pattern": {
        "pattern_score": 90,
        "pattern_id": "w_bottom",
        "pattern_name": "W底（雙底）",
        "failure_stop": 97.5,
        "target_price": 106.1,
        "dual_confirm": true,
        "pattern_bonus": 50
      }
    },
    {
      "ticker": "2836",
      "alpha_5d": 0.0966,
      "alpha_20d": 0.1805,
      "alpha_60d": 0.1001,
      "sharpe": 7.745,
      "confidence": "高信心",
      "uncertainty": 0.0228,
      "suggested_weight": 0.0974,
      "score": 105,
      "base_score": 55,
      "conditions_met": 2,
      "conditions_total": 4,
      "rank_stability": {
        "met": true,
        "detail": "Top 10 連續 2 天",
        "top10_streak": 2,
        "top50_streak": 4
      },
      "high_confidence": {
        "met": true,
        "detail": "Uncertainty=0.0228 ✓ (<0.0258)"
      },
      "relative_low": {
        "met": false,
        "detail": "RSI=60, 價格>MA20",
        "rsi": 60.0,
        "below_ma20": false
      },
      "institutional_buy": {
        "met": false,
        "detail": "無此股機構資料"
      },
      "pattern": {
        "pattern_score": 96,
        "pattern_id": "w_bottom",
        "pattern_name": "W底（雙底）",
        "failure_stop": 11.85,
        "target_price": 13.32,
        "dual_confirm": true,
        "pattern_bonus": 50
      }
    },
    {
      "ticker": "2540",
      "alpha_5d": 0.1499,
      "alpha_20d": 0.3433,
      "alpha_60d": 0.264,
      "sharpe": 7.649,
      "confidence": "低信心",
      "uncertainty": 0.0444,
      "suggested_weight": 0.0959,
      "score": 100,
      "base_score": 50,
      "conditions_met": 2,
      "conditions_total": 4,
      "rank_stability": {
        "met": true,
        "detail": "Top 10 連續 3 天",
        "top10_streak": 3,
        "top50_streak": 5
      },
      "high_confidence": {
        "met": false,
        "detail": "Uncertainty=0.0444 (需 <0.0258)"
      },
      "relative_low": {
        "met": true,
        "detail": "RSI=50, 價格<MA20 (53.5<53.8)",
        "rsi": 50.4,
        "below_ma20": true
      },
      "institutional_buy": {
        "met": false,
        "detail": "無此股機構資料"
      },
      "pattern": {
        "pattern_score": 96,
        "pattern_id": "spring_w",
        "pattern_name": "彈簧型W底",
        "failure_stop": 50.0,
        "target_price": 54.0,
        "dual_confirm": true,
        "pattern_bonus": 50
      }
    },
    {
      "ticker": "9942",
      "alpha_5d": 0.0756,
      "alpha_20d": 0.1315,
      "alpha_60d": 0.1069,
      "sharpe": 6.581,
      "confidence": "高信心",
      "uncertainty": 0.0194,
      "suggested_weight": 0.0828,
      "score": 85,
      "base_score": 45,
      "conditions_met": 2,
      "conditions_total": 4,
      "rank_stability": {
        "met": false,
        "detail": "Top 50 1 天 (需 ≥3)",
        "top10_streak": 1,
        "top50_streak": 1
      },
      "high_confidence": {
        "met": true,
        "detail": "Uncertainty=0.0194 ✓ (<0.0258)"
      },
      "relative_low": {
        "met": true,
        "detail": "RSI=48, 價格<MA20 (118.5<118.6)",
        "rsi": 47.9,
        "below_ma20": true
      },
      "institutional_buy": {
        "met": false,
        "detail": "無此股機構資料"
      },
      "pattern": {
        "pattern_score": 81,
        "pattern_id": "w_bottom",
        "pattern_name": "W底（雙底）",
        "failure_stop": 116.5,
        "target_price": 126.5,
        "dual_confirm": true,
        "pattern_bonus": 40
      }
    },
    {
      "ticker": "6214",
      "alpha_5d": 0.0604,
      "alpha_20d": 0.1228,
      "alpha_60d": 0.159,
      "sharpe": 6.173,
      "confidence": "高信心",
      "uncertainty": 0.0192,
      "suggested_weight": 0.077,
      "score": 75,
      "base_score": 45,
      "conditions_met": 2,
      "conditions_total": 4,
      "rank_stability": {
        "met": false,
        "detail": "未進入 Top 50",
        "top10_streak": 0,
        "top50_streak": 0
      },
      "high_confidence": {
        "met": true,
        "detail": "Uncertainty=0.0192 ✓ (<0.0258)"
      },
      "relative_low": {
        "met": true,
        "detail": "RSI=54, 價格<MA20 (143.0<146.3)",
        "rsi": 54.1,
        "below_ma20": true
      },
      "institutional_buy": {
        "met": false,
        "detail": "無此股機構資料"
      },
      "pattern": {
        "pattern_score": 68,
        "pattern_id": "w_bottom",
        "pattern_name": "W底（雙底）",
        "failure_stop": 105.0,
        "target_price": 121.25,
        "dual_confirm": true,
        "pattern_bonus": 30
      }
    },
    {
      "ticker": "2645",
      "alpha_5d": 0.0976,
      "alpha_20d": 0.134,
      "alpha_60d": 0.081,
      "sharpe": 7.26,
      "confidence": "高信心",
      "uncertainty": 0.0179,
      "suggested_weight": 0.0916,
      "score": 55,
      "base_score": 55,
      "conditions_met": 2,
      "conditions_total": 4,
      "rank_stability": {
        "met": true,
        "detail": "Top 50 連續 5 天",
        "top10_streak": 0,
        "top50_streak": 5
      },
      "high_confidence": {
        "met": true,
        "detail": "Uncertainty=0.0179 ✓ (<0.0258)"
      },
      "relative_low": {
        "met": false,
        "detail": "RSI=57, 價格>MA20",
        "rsi": 57.5,
        "below_ma20": false
      },
      "institutional_buy": {
        "met": false,
        "detail": "無此股機構資料"
      },
      "pattern": null
    },
    {
      "ticker": "2850",
      "alpha_5d": 0.1172,
      "alpha_20d": 0.1771,
      "alpha_60d": 0.119,
      "sharpe": 7.243,
      "confidence": "高信心",
      "uncertainty": 0.0239,
      "suggested_weight": 0.0901,
      "score": 55,
      "base_score": 55,
      "conditions_met": 2,
      "conditions_total": 4,
      "rank_stability": {
        "met": true,
        "detail": "Top 50 連續 5 天",
        "top10_streak": 0,
        "top50_streak": 5
      },
      "high_confidence": {
        "met": true,
        "detail": "Uncertainty=0.0239 ✓ (<0.0258)"
      },
      "relative_low": {
        "met": false,
        "detail": "RSI=62, 價格>MA20",
        "rsi": 61.8,
        "below_ma20": false
      },
      "institutional_buy": {
        "met": false,
        "detail": "無此股機構資料"
      },
      "pattern": null
    },
    {
      "ticker": "1423",
      "alpha_5d": 0.1006,
      "alpha_20d": 0.1848,
      "alpha_60d": 0.1485,
      "sharpe": 7.238,
      "confidence": "高信心",
      "uncertainty": 0.025,
      "suggested_weight": 0.0901,
      "score": 55,
      "base_score": 55,
      "conditions_met": 2,
      "conditions_total": 4,
      "rank_stability": {
        "met": true,
        "detail": "Top 50 連續 4 天",
        "top10_streak": 0,
        "top50_streak": 4
      },
      "high_confidence": {
        "met": true,
        "detail": "Uncertainty=0.0250 ✓ (<0.0258)"
      },
      "relative_low": {
        "met": false,
        "detail": "RSI=74, 價格>MA20",
        "rsi": 74.5,
        "below_ma20": false
      },
      "institutional_buy": {
        "met": false,
        "detail": "無此股機構資料"
      },
      "pattern": null
    },
    {
      "ticker": "6994",
      "alpha_5d": 0.584,
      "alpha_20d": 0.7443,
      "alpha_60d": 0.4169,
      "sharpe": 6.689,
      "confidence": "低信心",
      "uncertainty": 0.1107,
      "suggested_weight": 0.0843,
      "score": 50,
      "base_score": 50,
      "conditions_met": 2,
      "conditions_total": 4,
      "rank_stability": {
        "met": true,
        "detail": "Top 50 連續 4 天",
        "top10_streak": 0,
        "top50_streak": 4
      },
      "high_confidence": {
        "met": false,
        "detail": "Uncertainty=0.1107 (需 <0.0258)"
      },
      "relative_low": {
        "met": true,
        "detail": "RSI=41, 價格<MA20 (57.1<59.0)",
        "rsi": 40.9,
        "below_ma20": true
      },
      "institutional_buy": {
        "met": false,
        "detail": "無此股機構資料"
      },
      "pattern": null
    },
    {
      "ticker": "8349",
      "alpha_5d": 0.0828,
      "alpha_20d": 0.1281,
      "alpha_60d": 0.0201,
      "sharpe": 6.801,
      "confidence": "高信心",
      "uncertainty": 0.0182,
      "suggested_weight": 0.0858,
      "score": 45,
      "base_score": 45,
      "conditions_met": 2,
      "conditions_total": 4,
      "rank_stability": {
        "met": false,
        "detail": "未進入 Top 50",
        "top10_streak": 0,
        "top50_streak": 0
      },
      "high_confidence": {
        "met": true,
        "detail": "Uncertainty=0.0182 ✓ (<0.0258)"
      },
      "relative_low": {
        "met": true,
        "detail": "RSI=37, 價格<MA20 (40.9<41.7)",
        "rsi": 37.3,
        "below_ma20": true
      },
      "institutional_buy": {
        "met": false,
        "detail": "無此股機構資料"
      },
      "pattern": null
    }
  ],
  "exit_signals": [],
  "watch_list": [
    {
      "ticker": "5515",
      "alpha_5d": 0.116,
      "alpha_20d": 0.2928,
      "alpha_60d": 0.2993,
      "sharpe": 9.344,
      "confidence": "中信心",
      "uncertainty": 0.0309,
      "suggested_weight": 0.0081,
      "score": 30,
      "base_score": 30,
      "conditions_met": 1,
      "conditions_total": 4,
      "rank_stability": {
        "met": true,
        "detail": "Top 50 連續 5 天",
        "top10_streak": 1,
        "top50_streak": 5
      },
      "high_confidence": {
        "met": false,
        "detail": "Uncertainty=0.0309 (需 <0.0258)"
      },
      "relative_low": {
        "met": false,
        "detail": "RSI=71, 價格>MA20",
        "rsi": 71.2,
        "below_ma20": false
      },
      "institutional_buy": {
        "met": false,
        "detail": "無此股機構資料"
      },
      "pattern": null
    },
    {
      "ticker": "2069",
      "alpha_5d": 0.1101,
      "alpha_20d": 0.2067,
      "alpha_60d": 0.1915,
      "sharpe": 9.076,
      "confidence": "高信心",
      "uncertainty": 0.0223,
      "suggested_weight": 0.0078,
      "score": 65,
      "base_score": 25,
      "conditions_met": 1,
      "conditions_total": 4,
      "rank_stability": {
        "met": false,
        "detail": "Top 50 1 天 (需 ≥3)",
        "top10_streak": 0,
        "top50_streak": 1
      },
      "high_confidence": {
        "met": true,
        "detail": "Uncertainty=0.0223 ✓ (<0.0258)"
      },
      "relative_low": {
        "met": false,
        "detail": "RSI=59, 價格>MA20",
        "rsi": 59.4,
        "below_ma20": false
      },
      "institutional_buy": {
        "met": false,
        "detail": "無此股機構資料"
      },
      "pattern": {
        "pattern_score": 87,
        "pattern_id": "w_bottom",
        "pattern_name": "W底（雙底）",
        "failure_stop": 18.45,
        "target_price": 19.92,
        "dual_confirm": true,
        "pattern_bonus": 40
      }
    },
    {
      "ticker": "2597",
      "alpha_5d": 0.1749,
      "alpha_20d": 0.2409,
      "alpha_60d": 0.1759,
      "sharpe": 8.547,
      "confidence": "中信心",
      "uncertainty": 0.0277,
      "suggested_weight": 0.0074,
      "score": 30,
      "base_score": 30,
      "conditions_met": 1,
      "conditions_total": 4,
      "rank_stability": {
        "met": true,
        "detail": "Top 50 連續 5 天",
        "top10_streak": 0,
        "top50_streak": 5
      },
      "high_confidence": {
        "met": false,
        "detail": "Uncertainty=0.0277 (需 <0.0258)"
      },
      "relative_low": {
        "met": false,
        "detail": "RSI=66, 價格>MA20",
        "rsi": 66.0,
        "below_ma20": false
      },
      "institutional_buy": {
        "met": false,
        "detail": "無此股機構資料"
      },
      "pattern": null
    },
    {
      "ticker": "2546",
      "alpha_5d": 0.0867,
      "alpha_20d": 0.1726,
      "alpha_60d": 0.1374,
      "sharpe": 8.374,
      "confidence": "高信心",
      "uncertainty": 0.0201,
      "suggested_weight": 0.0072,
      "score": 25,
      "base_score": 25,
      "conditions_met": 1,
      "conditions_total": 4,
      "rank_stability": {
        "met": false,
        "detail": "Top 50 1 天 (需 ≥3)",
        "top10_streak": 1,
        "top50_streak": 1
      },
      "high_confidence": {
        "met": true,
        "detail": "Uncertainty=0.0201 ✓ (<0.0258)"
      },
      "relative_low": {
        "met": false,
        "detail": "RSI=88, 價格>MA20",
        "rsi": 87.9,
        "below_ma20": false
      },
      "institutional_buy": {
        "met": false,
        "detail": "無此股機構資料"
      },
      "pattern": null
    },
    {
      "ticker": "55",
      "alpha_5d": 0.3257,
      "alpha_20d": 0.5895,
      "alpha_60d": 0.5634,
      "sharpe": 7.961,
      "confidence": "低信心",
      "uncertainty": 0.0735,
      "suggested_weight": 0.0069,
      "score": 30,
      "base_score": 30,
      "conditions_met": 1,
      "conditions_total": 4,
      "rank_stability": {
        "met": true,
        "detail": "Top 50 連續 5 天",
        "top10_streak": 1,
        "top50_streak": 5
      },
      "high_confidence": {
        "met": false,
        "detail": "Uncertainty=0.0735 (需 <0.0258)"
      },
      "relative_low": {
        "met": false,
        "detail": "無價格資料",
        "rsi": null,
        "below_ma20": null
      },
      "institutional_buy": {
        "met": false,
        "detail": "無此股機構資料"
      },
      "pattern": null
    },
    {
      "ticker": "5522",
      "alpha_5d": 0.1088,
      "alpha_20d": 0.1737,
      "alpha_60d": 0.1373,
      "sharpe": 7.931,
      "confidence": "高信心",
      "uncertainty": 0.0214,
      "suggested_weight": 0.0068,
      "score": 25,
      "base_score": 25,
      "conditions_met": 1,
      "conditions_total": 4,
      "rank_stability": {
        "met": false,
        "detail": "未進入 Top 50",
        "top10_streak": 0,
        "top50_streak": 0
      },
      "high_confidence": {
        "met": true,
        "detail": "Uncertainty=0.0214 ✓ (<0.0258)"
      },
      "relative_low": {
        "met": false,
        "detail": "RSI=60, 價格>MA20",
        "rsi": 59.9,
        "below_ma20": false
      },
      "institutional_buy": {
        "met": false,
        "detail": "無此股機構資料"
      },
      "pattern": null
    },
    {
      "ticker": "2852",
      "alpha_5d": 0.0945,
      "alpha_20d": 0.1877,
      "alpha_60d": 0.1765,
      "sharpe": 7.445,
      "confidence": "高信心",
      "uncertainty": 0.0247,
      "suggested_weight": 0.0064,
      "score": 25,
      "base_score": 25,
      "conditions_met": 1,
      "conditions_total": 4,
      "rank_stability": {
        "met": false,
        "detail": "Top 50 2 天 (需 ≥3)",
        "top10_streak": 0,
        "top50_streak": 2
      },
      "high_confidence": {
        "met": true,
        "detail": "Uncertainty=0.0247 ✓ (<0.0258)"
      },
      "relative_low": {
        "met": false,
        "detail": "RSI=64, 價格>MA20",
        "rsi": 64.0,
        "below_ma20": false
      },
      "institutional_buy": {
        "met": false,
        "detail": "無此股機構資料"
      },
      "pattern": null
    },
    {
      "ticker": "1720",
      "alpha_5d": 0.0873,
      "alpha_20d": 0.1423,
      "alpha_60d": 0.1259,
      "sharpe": 7.333,
      "confidence": "高信心",
      "uncertainty": 0.0189,
      "suggested_weight": 0.0063,
      "score": 55,
      "base_score": 25,
      "conditions_met": 1,
      "conditions_total": 4,
      "rank_stability": {
        "met": false,
        "detail": "未進入 Top 50",
        "top10_streak": 0,
        "top50_streak": 0
      },
      "high_confidence": {
        "met": true,
        "detail": "Uncertainty=0.0189 ✓ (<0.0258)"
      },
      "relative_low": {
        "met": false,
        "detail": "RSI=59, 價格>MA20",
        "rsi": 58.9,
        "below_ma20": false
      },
      "institutional_buy": {
        "met": false,
        "detail": "無此股機構資料"
      },
      "pattern": {
        "pattern_score": 74,
        "pattern_id": "w_bottom",
        "pattern_name": "W底（雙底）",
        "failure_stop": 60.7,
        "target_price": 66.9,
        "dual_confirm": true,
        "pattern_bonus": 30
      }
    },
    {
      "ticker": "2889",
      "alpha_5d": 0.1332,
      "alpha_20d": 0.2683,
      "alpha_60d": 0.2006,
      "sharpe": 7.276,
      "confidence": "中信心",
      "uncertainty": 0.0363,
      "suggested_weight": 0.0063,
      "score": 30,
      "base_score": 30,
      "conditions_met": 1,
      "conditions_total": 4,
      "rank_stability": {
        "met": true,
        "detail": "Top 10 連續 2 天",
        "top10_streak": 2,
        "top50_streak": 5
      },
      "high_confidence": {
        "met": false,
        "detail": "Uncertainty=0.0363 (需 <0.0258)"
      },
      "relative_low": {
        "met": false,
        "detail": "RSI=54, 價格>MA20",
        "rsi": 54.2,
        "below_ma20": false
      },
      "institutional_buy": {
        "met": false,
        "detail": "無此股機構資料"
      },
      "pattern": null
    },
    {
      "ticker": "5609",
      "alpha_5d": 0.0715,
      "alpha_20d": 0.1349,
      "alpha_60d": 0.1325,
      "sharpe": 6.885,
      "confidence": "高信心",
      "uncertainty": 0.019,
      "suggested_weight": 0.0059,
      "score": 75,
      "base_score": 25,
      "conditions_met": 1,
      "conditions_total": 4,
      "rank_stability": {
        "met": false,
        "detail": "未進入 Top 50",
        "top10_streak": 0,
        "top50_streak": 0
      },
      "high_confidence": {
        "met": true,
        "detail": "Uncertainty=0.0190 ✓ (<0.0258)"
      },
      "relative_low": {
        "met": false,
        "detail": "RSI=64, 價格>MA20",
        "rsi": 63.7,
        "below_ma20": false
      },
      "institutional_buy": {
        "met": false,
        "detail": "無此股機構資料"
      },
      "pattern": {
        "pattern_score": 92,
        "pattern_id": "w_bottom",
        "pattern_name": "W底（雙底）",
        "failure_stop": 77.1,
        "target_price": 83.8,
        "dual_confirm": true,
        "pattern_bonus": 50
      }
    },
    {
      "ticker": "2897",
      "alpha_5d": 0.0504,
      "alpha_20d": 0.1367,
      "alpha_60d": 0.0967,
      "sharpe": 6.706,
      "confidence": "高信心",
      "uncertainty": 0.0198,
      "suggested_weight": 0.0058,
      "score": 25,
      "base_score": 25,
      "conditions_met": 1,
      "conditions_total": 4,
      "rank_stability": {
        "met": false,
        "detail": "Top 50 1 天 (需 ≥3)",
        "top10_streak": 0,
        "top50_streak": 1
      },
      "high_confidence": {
        "met": true,
        "detail": "Uncertainty=0.0198 ✓ (<0.0258)"
      },
      "relative_low": {
        "met": false,
        "detail": "RSI=62, 價格>MA20",
        "rsi": 62.3,
        "below_ma20": false
      },
      "institutional_buy": {
        "met": false,
        "detail": "無此股機構資料"
      },
      "pattern": null
    },
    {
      "ticker": "5478",
      "alpha_5d": 0.1052,
      "alpha_20d": 0.1399,
      "alpha_60d": 0.1696,
      "sharpe": 6.533,
      "confidence": "高信心",
      "uncertainty": 0.0208,
      "suggested_weight": 0.0056,
      "score": 65,
      "base_score": 25,
      "conditions_met": 1,
      "conditions_total": 4,
      "rank_stability": {
        "met": false,
        "detail": "Top 50 1 天 (需 ≥3)",
        "top10_streak": 0,
        "top50_streak": 1
      },
      "high_confidence": {
        "met": true,
        "detail": "Uncertainty=0.0208 ✓ (<0.0258)"
      },
      "relative_low": {
        "met": false,
        "detail": "RSI=59, 價格>MA20",
        "rsi": 58.8,
        "below_ma20": false
      },
      "institutional_buy": {
        "met": false,
        "detail": "無此股機構資料"
      },
      "pattern": {
        "pattern_score": 88,
        "pattern_id": "w_bottom",
        "pattern_name": "W底（雙底）",
        "failure_stop": 94.58,
        "target_price": 119.03,
        "dual_confirm": true,
        "pattern_bonus": 40
      }
    },
    {
      "ticker": "6625",
      "alpha_5d": 0.0629,
      "alpha_20d": 0.1486,
      "alpha_60d": 0.1624,
      "sharpe": 6.483,
      "confidence": "高信心",
      "uncertainty": 0.0223,
      "suggested_weight": 0.0056,
      "score": 25,
      "base_score": 25,
      "conditions_met": 1,
      "conditions_total": 4,
      "rank_stability": {
        "met": false,
        "detail": "Top 50 2 天 (需 ≥3)",
        "top10_streak": 0,
        "top50_streak": 2
      },
      "high_confidence": {
        "met": true,
        "detail": "Uncertainty=0.0223 ✓ (<0.0258)"
      },
      "relative_low": {
        "met": false,
        "detail": "RSI=69, 價格>MA20",
        "rsi": 69.4,
        "below_ma20": false
      },
      "institutional_buy": {
        "met": false,
        "detail": "無此股機構資料"
      },
      "pattern": null
    },
    {
      "ticker": "5258",
      "alpha_5d": 0.1136,
      "alpha_20d": 0.1588,
      "alpha_60d": 0.0948,
      "sharpe": 6.379,
      "confidence": "高信心",
      "uncertainty": 0.0243,
      "suggested_weight": 0.0055,
      "score": 25,
      "base_score": 25,
      "conditions_met": 1,
      "conditions_total": 4,
      "rank_stability": {
        "met": false,
        "detail": "未進入 Top 50",
        "top10_streak": 0,
        "top50_streak": 0
      },
      "high_confidence": {
        "met": true,
        "detail": "Uncertainty=0.0243 ✓ (<0.0258)"
      },
      "relative_low": {
        "met": false,
        "detail": "RSI=48, 價格>MA20",
        "rsi": 47.8,
        "below_ma20": false
      },
      "institutional_buy": {
        "met": false,
        "detail": "無此股機構資料"
      },
      "pattern": null
    },
    {
      "ticker": "6177",
      "alpha_5d": 0.0834,
      "alpha_20d": 0.1627,
      "alpha_60d": 0.1678,
      "sharpe": 6.323,
      "confidence": "高信心",
      "uncertainty": 0.0251,
      "suggested_weight": 0.0055,
      "score": 75,
      "base_score": 25,
      "conditions_met": 1,
      "conditions_total": 4,
      "rank_stability": {
        "met": false,
        "detail": "Top 50 1 天 (需 ≥3)",
        "top10_streak": 0,
        "top50_streak": 1
      },
      "high_confidence": {
        "met": true,
        "detail": "Uncertainty=0.0251 ✓ (<0.0258)"
      },
      "relative_low": {
        "met": false,
        "detail": "RSI=62, 價格>MA20",
        "rsi": 61.9,
        "below_ma20": false
      },
      "institutional_buy": {
        "met": false,
        "detail": "無此股機構資料"
      },
      "pattern": {
        "pattern_score": 93,
        "pattern_id": "w_bottom",
        "pattern_name": "W底（雙底）",
        "failure_stop": 44.5,
        "target_price": 52.12,
        "dual_confirm": true,
        "pattern_bonus": 50
      }
    },
    {
      "ticker": "2617",
      "alpha_5d": 0.0306,
      "alpha_20d": 0.1096,
      "alpha_60d": 0.0762,
      "sharpe": 6.301,
      "confidence": "高信心",
      "uncertainty": 0.0167,
      "suggested_weight": 0.0054,
      "score": 65,
      "base_score": 25,
      "conditions_met": 1,
      "conditions_total": 4,
      "rank_stability": {
        "met": false,
        "detail": "未進入 Top 50",
        "top10_streak": 0,
        "top50_streak": 0
      },
      "high_confidence": {
        "met": true,
        "detail": "Uncertainty=0.0167 ✓ (<0.0258)"
      },
      "relative_low": {
        "met": false,
        "detail": "RSI=64, 價格>MA20",
        "rsi": 63.9,
        "below_ma20": false
      },
      "institutional_buy": {
        "met": false,
        "detail": "無此股機構資料"
      },
      "pattern": {
        "pattern_score": 84,
        "pattern_id": "w_bottom",
        "pattern_name": "W底（雙底）",
        "failure_stop": 28.65,
        "target_price": 30.68,
        "dual_confirm": true,
        "pattern_bonus": 40
      }
    },
    {
      "ticker": "5607",
      "alpha_5d": 0.0934,
      "alpha_20d": 0.164,
      "alpha_60d": 0.1084,
      "sharpe": 6.297,
      "confidence": "高信心",
      "uncertainty": 0.0254,
      "suggested_weight": 0.0054,
      "score": 25,
      "base_score": 25,
      "conditions_met": 1,
      "conditions_total": 4,
      "rank_stability": {
        "met": false,
        "detail": "Top 50 1 天 (需 ≥3)",
        "top10_streak": 0,
        "top50_streak": 1
      },
      "high_confidence": {
        "met": true,
        "detail": "Uncertainty=0.0254 ✓ (<0.0258)"
      },
      "relative_low": {
        "met": false,
        "detail": "RSI=57, 價格>MA20",
        "rsi": 57.0,
        "below_ma20": false
      },
      "institutional_buy": {
        "met": false,
        "detail": "無此股機構資料"
      },
      "pattern": null
    },
    {
      "ticker": "5410",
      "alpha_5d": 0.3144,
      "alpha_20d": 0.3832,
      "alpha_60d": 0.3329,
      "sharpe": 6.264,
      "confidence": "低信心",
      "uncertainty": 0.0605,
      "suggested_weight": 0.0054,
      "score": 80,
      "base_score": 30,
      "conditions_met": 1,
      "conditions_total": 4,
      "rank_stability": {
        "met": true,
        "detail": "Top 50 連續 5 天",
        "top10_streak": 0,
        "top50_streak": 5
      },
      "high_confidence": {
        "met": false,
        "detail": "Uncertainty=0.0605 (需 <0.0258)"
      },
      "relative_low": {
        "met": false,
        "detail": "RSI=84, 價格>MA20",
        "rsi": 83.6,
        "below_ma20": false
      },
      "institutional_buy": {
        "met": false,
        "detail": "無此股機構資料"
      },
      "pattern": {
        "pattern_score": 100,
        "pattern_id": "w_bottom",
        "pattern_name": "W底（雙底）",
        "failure_stop": 29.25,
        "target_price": 34.52,
        "dual_confirm": true,
        "pattern_bonus": 50
      }
    },
    {
      "ticker": "1734",
      "alpha_5d": 0.073,
      "alpha_20d": 0.1477,
      "alpha_60d": 0.1035,
      "sharpe": 6.111,
      "confidence": "高信心",
      "uncertainty": 0.0235,
      "suggested_weight": 0.0053,
      "score": 75,
      "base_score": 25,
      "conditions_met": 1,
      "conditions_total": 4,
      "rank_stability": {
        "met": false,
        "detail": "Top 50 1 天 (需 ≥3)",
        "top10_streak": 1,
        "top50_streak": 1
      },
      "high_confidence": {
        "met": true,
        "detail": "Uncertainty=0.0235 ✓ (<0.0258)"
      },
      "relative_low": {
        "met": false,
        "detail": "RSI=61, 價格>MA20",
        "rsi": 60.7,
        "below_ma20": false
      },
      "institutional_buy": {
        "met": false,
        "detail": "無此股機構資料"
      },
      "pattern": {
        "pattern_score": 97,
        "pattern_id": "w_bottom",
        "pattern_name": "W底（雙底）",
        "failure_stop": 30.2,
        "target_price": 32.35,
        "dual_confirm": true,
        "pattern_bonus": 50
      }
    },
    {
      "ticker": "1909",
      "alpha_5d": 0.0864,
      "alpha_20d": 0.1608,
      "alpha_60d": 0.1339,
      "sharpe": 6.092,
      "confidence": "高信心",
      "uncertainty": 0.0257,
      "suggested_weight": 0.0053,
      "score": 65,
      "base_score": 25,
      "conditions_met": 1,
      "conditions_total": 4,
      "rank_stability": {
        "met": false,
        "detail": "Top 50 1 天 (需 ≥3)",
        "top10_streak": 0,
        "top50_streak": 1
      },
      "high_confidence": {
        "met": true,
        "detail": "Uncertainty=0.0257 ✓ (<0.0258)"
      },
      "relative_low": {
        "met": false,
        "detail": "RSI=68, 價格>MA20",
        "rsi": 67.9,
        "below_ma20": false
      },
      "institutional_buy": {
        "met": false,
        "detail": "無此股機構資料"
      },
      "pattern": {
        "pattern_score": 84,
        "pattern_id": "w_bottom",
        "pattern_name": "W底（雙底）",
        "failure_stop": 8.9,
        "target_price": 9.61,
        "dual_confirm": true,
        "pattern_bonus": 40
      }
    },
    {
      "ticker": "3022",
      "alpha_5d": 0.0733,
      "alpha_20d": 0.1282,
      "alpha_60d": 0.1206,
      "sharpe": 6.076,
      "confidence": "高信心",
      "uncertainty": 0.0204,
      "suggested_weight": 0.0052,
      "score": 25,
      "base_score": 25,
      "conditions_met": 1,
      "conditions_total": 4,
      "rank_stability": {
        "met": false,
        "detail": "未進入 Top 50",
        "top10_streak": 0,
        "top50_streak": 0
      },
      "high_confidence": {
        "met": true,
        "detail": "Uncertainty=0.0204 ✓ (<0.0258)"
      },
      "relative_low": {
        "met": false,
        "detail": "RSI=68, 價格>MA20",
        "rsi": 68.3,
        "below_ma20": false
      },
      "institutional_buy": {
        "met": false,
        "detail": "無此股機構資料"
      },
      "pattern": null
    },
    {
      "ticker": "2607",
      "alpha_5d": 0.0319,
      "alpha_20d": 0.1147,
      "alpha_60d": 0.0547,
      "sharpe": 5.926,
      "confidence": "高信心",
      "uncertainty": 0.0187,
      "suggested_weight": 0.0051,
      "score": 75,
      "base_score": 25,
      "conditions_met": 1,
      "conditions_total": 4,
      "rank_stability": {
        "met": false,
        "detail": "未進入 Top 50",
        "top10_streak": 0,
        "top50_streak": 0
      },
      "high_confidence": {
        "met": true,
        "detail": "Uncertainty=0.0187 ✓ (<0.0258)"
      },
      "relative_low": {
        "met": false,
        "detail": "RSI=64, 價格>MA20",
        "rsi": 63.5,
        "below_ma20": false
      },
      "institutional_buy": {
        "met": false,
        "detail": "無此股機構資料"
      },
      "pattern": {
        "pattern_score": 94,
        "pattern_id": "spring_w",
        "pattern_name": "彈簧型W底",
        "failure_stop": 46.45,
        "target_price": 50.35,
        "dual_confirm": true,
        "pattern_bonus": 50
      }
    },
    {
      "ticker": "6024",
      "alpha_5d": 0.053,
      "alpha_20d": 0.1227,
      "alpha_60d": 0.0801,
      "sharpe": 5.883,
      "confidence": "高信心",
      "uncertainty": 0.0202,
      "suggested_weight": 0.0051,
      "score": 25,
      "base_score": 25,
      "conditions_met": 1,
      "conditions_total": 4,
      "rank_stability": {
        "met": false,
        "detail": "Top 50 1 天 (需 ≥3)",
        "top10_streak": 0,
        "top50_streak": 1
      },
      "high_confidence": {
        "met": true,
        "detail": "Uncertainty=0.0202 ✓ (<0.0258)"
      },
      "relative_low": {
        "met": false,
        "detail": "RSI=73, 價格>MA20",
        "rsi": 73.4,
        "below_ma20": false
      },
      "institutional_buy": {
        "met": false,
        "detail": "無此股機構資料"
      },
      "pattern": null
    },
    {
      "ticker": "2636",
      "alpha_5d": 0.042,
      "alpha_20d": 0.1121,
      "alpha_60d": 0.071,
      "sharpe": 5.864,
      "confidence": "高信心",
      "uncertainty": 0.0184,
      "suggested_weight": 0.0051,
      "score": 25,
      "base_score": 25,
      "conditions_met": 1,
      "conditions_total": 4,
      "rank_stability": {
        "met": false,
        "detail": "未進入 Top 50",
        "top10_streak": 0,
        "top50_streak": 0
      },
      "high_confidence": {
        "met": true,
        "detail": "Uncertainty=0.0184 ✓ (<0.0258)"
      },
      "relative_low": {
        "met": false,
        "detail": "RSI=68, 價格>MA20",
        "rsi": 68.3,
        "below_ma20": false
      },
      "institutional_buy": {
        "met": false,
        "detail": "無此股機構資料"
      },
      "pattern": null
    },
    {
      "ticker": "2851",
      "alpha_5d": 0.0587,
      "alpha_20d": 0.1251,
      "alpha_60d": 0.1164,
      "sharpe": 5.856,
      "confidence": "高信心",
      "uncertainty": 0.0207,
      "suggested_weight": 0.0051,
      "score": 75,
      "base_score": 25,
      "conditions_met": 1,
      "conditions_total": 4,
      "rank_stability": {
        "met": false,
        "detail": "Top 50 1 天 (需 ≥3)",
        "top10_streak": 0,
        "top50_streak": 1
      },
      "high_confidence": {
        "met": true,
        "detail": "Uncertainty=0.0207 ✓ (<0.0258)"
      },
      "relative_low": {
        "met": false,
        "detail": "RSI=70, 價格>MA20",
        "rsi": 69.7,
        "below_ma20": false
      },
      "institutional_buy": {
        "met": false,
        "detail": "無此股機構資料"
      },
      "pattern": {
        "pattern_score": 91,
        "pattern_id": "w_bottom",
        "pattern_name": "W底（雙底）",
        "failure_stop": 26.55,
        "target_price": 29.02,
        "dual_confirm": true,
        "pattern_bonus": 50
      }
    }
  ],
  "portfolio_check": {
    "n_positions": 11,
    "warnings": []
  }
}