{
  "date": "2026-07-20",
  "generated_at": "2026-07-20T19:40:57",
  "taiex_technicals": {
    "close": 42450.0,
    "ma_20": 45650.0,
    "ma_60": 43601.0,
    "ma_120": 43601.0,
    "rsi_14": 36.89,
    "macd": -145.43,
    "macd_signal": 362.15,
    "macd_hist": -507.58,
    "kd_k": 22.47,
    "kd_d": 32.0,
    "bb_pct_b": -0.097,
    "bias_20ma": -7.01,
    "atr_14": 1262.55,
    "obv_trend": "down",
    "realized_vol_10d": 35.84,
    "beta_vs_spx": 0.0,
    "tech_radar": [
      {
        "subject": "RSI 動能",
        "A": 37
      },
      {
        "subject": "MACD 趨勢",
        "A": 10
      },
      {
        "subject": "KD 隨機",
        "A": 22
      },
      {
        "subject": "Bollinger",
        "A": 0
      },
      {
        "subject": "MA 排列",
        "A": 50
      },
      {
        "subject": "ATR 波動",
        "A": 15
      }
    ],
    "table": [
      {
        "label": "RSI(14)",
        "value": "36.89",
        "status": "偏空",
        "color": "var(--negative)"
      },
      {
        "label": "MACD",
        "value": "-145.4",
        "status": "偏空",
        "color": "var(--negative)"
      },
      {
        "label": "KD(9,3,3) K",
        "value": "22.47",
        "status": "偏空",
        "color": "var(--negative)"
      },
      {
        "label": "KD D值",
        "value": "32.0",
        "status": "死亡交叉",
        "color": "var(--negative)"
      },
      {
        "label": "Bollinger %B",
        "value": "-0.10",
        "status": "下軌趨近",
        "color": "var(--negative)"
      },
      {
        "label": "乖離率(20MA)",
        "value": "-7.01%",
        "status": "偏低",
        "color": "var(--accent-amber)"
      },
      {
        "label": "ATR(14)",
        "value": "1262.5",
        "status": "波動正常",
        "color": "var(--text-muted)"
      },
      {
        "label": "OBV 趨勢",
        "value": "下降",
        "status": "量能背離",
        "color": "var(--negative)"
      }
    ],
    "risk_metrics": [
      {
        "label": "10日實現波動率",
        "value": "35.8%",
        "desc": "年化"
      },
      {
        "label": "台股 Beta (vs SPX)",
        "value": "0.0",
        "desc": "近60日"
      },
      {
        "label": "MA 20",
        "value": "45,650",
        "desc": "20日均線"
      },
      {
        "label": "MA 60",
        "value": "43,601",
        "desc": "60日均線"
      }
    ]
  },
  "institutional": {
    "foreign_net_5d_bn": -192608465.4,
    "investment_trust_net_5d_bn": 28879447.0,
    "dealer_net_5d_bn": 34208423.3,
    "total_net_5d_bn": -129520595.1,
    "history": [
      {
        "date": "2026-07-14",
        "date_label": "07/14",
        "foreign_net": -31781545.6,
        "investment_trust_net": 14341930.9,
        "dealer_net": 2973605.3
      },
      {
        "date": "2026-07-15",
        "date_label": "07/15",
        "foreign_net": 10252014.7,
        "investment_trust_net": 9207177.8,
        "dealer_net": 13127719.4
      },
      {
        "date": "2026-07-16",
        "date_label": "07/16",
        "foreign_net": -9871682.5,
        "investment_trust_net": -1980874.3,
        "dealer_net": 1587692.0
      },
      {
        "date": "2026-07-17",
        "date_label": "07/17",
        "foreign_net": -187843121.6,
        "investment_trust_net": -2290830.2,
        "dealer_net": -950466.9
      },
      {
        "date": "2026-07-20",
        "date_label": "07/20",
        "foreign_net": 26635869.7,
        "investment_trust_net": 9602042.7,
        "dealer_net": 17469873.4
      }
    ]
  },
  "breadth_history": [
    {
      "date": "2026-07-14",
      "date_label": "07/14",
      "adv": 350,
      "dec": 1498,
      "ratio": 0.23
    },
    {
      "date": "2026-07-15",
      "date_label": "07/15",
      "adv": 1532,
      "dec": 311,
      "ratio": 4.93
    },
    {
      "date": "2026-07-16",
      "date_label": "07/16",
      "adv": 625,
      "dec": 1162,
      "ratio": 0.54
    },
    {
      "date": "2026-07-17",
      "date_label": "07/17",
      "adv": 144,
      "dec": 1752,
      "ratio": 0.08
    },
    {
      "date": "2026-07-20",
      "date_label": "07/20",
      "adv": 624,
      "dec": 1185,
      "ratio": 0.53
    }
  ],
  "margin": {
    "date": "2026-04-24",
    "margin_balance_bn": 0.0,
    "short_balance_bn": 0.0,
    "margin_ratio": 0.0
  },
  "sector_flow": [
    {
      "sector": "電子工業",
      "net_5d_bn": -4536817.3,
      "direction": "out"
    },
    {
      "sector": "半導體業",
      "net_5d_bn": -3740329.7,
      "direction": "out"
    },
    {
      "sector": "電子零組件業",
      "net_5d_bn": -658468.1,
      "direction": "out"
    },
    {
      "sector": "ETF",
      "net_5d_bn": -430334.2,
      "direction": "out"
    },
    {
      "sector": "塑膠工業",
      "net_5d_bn": -302979.4,
      "direction": "out"
    },
    {
      "sector": "通信網路業",
      "net_5d_bn": 259765.6,
      "direction": "in"
    },
    {
      "sector": "其他電子業",
      "net_5d_bn": -155547.1,
      "direction": "out"
    },
    {
      "sector": "航運業",
      "net_5d_bn": 131084.7,
      "direction": "in"
    }
  ]
}